<?xml version="1.0" encoding="utf-8"?>
<!-- This is a CI serialization file for /About-Us -->
<cms.node>
  <NodeACLID>
    <GUID>0072d163-58b7-495f-bbcd-1f15eaadf7e3</GUID>
    <ObjectType>cms.acl</ObjectType>
    <Site>
      <CodeName>DancingGoatCore</CodeName>
      <GUID>50ddc16b-9cd7-402f-af01-f3a3feae4ba2</GUID>
      <ObjectType>cms.site</ObjectType>
    </Site>
  </NodeACLID>
  <NodeAlias>About-Us</NodeAlias>
  <NodeClassID>
    <CodeName>DancingGoatCore.AboutUs</CodeName>
    <GUID>6adbb30c-0b8d-423e-b3f2-54a3f72266f0</GUID>
    <ObjectType>cms.documenttype</ObjectType>
  </NodeClassID>
  <NodeGUID>38ac32a4-57b3-47ea-b12c-85da4599b917</NodeGUID>
  <NodeIsACLOwner>False</NodeIsACLOwner>
  <NodeName>About Us</NodeName>
  <NodeOrder>4</NodeOrder>
  <NodeOwner>
    <CodeName>administrator</CodeName>
    <GUID>6415b8ce-8072-4bcd-8e48-9d7178b826b7</GUID>
    <ObjectType>cms.user</ObjectType>
  </NodeOwner>
  <NodeParentID>
    <CodeName>/</CodeName>
    <GUID>acdd2058-bde0-4c9d-8332-45f417220571</GUID>
    <ObjectType>cms.node</ObjectType>
    <Site>
      <CodeName>DancingGoatCore</CodeName>
      <GUID>50ddc16b-9cd7-402f-af01-f3a3feae4ba2</GUID>
      <ObjectType>cms.site</ObjectType>
    </Site>
  </NodeParentID>
  <NodeSiteID>
    <CodeName>DancingGoatCore</CodeName>
    <GUID>50ddc16b-9cd7-402f-af01-f3a3feae4ba2</GUID>
    <ObjectType>cms.site</ObjectType>
  </NodeSiteID>
</cms.node>