<?xml version="1.0" encoding="utf-8"?>
<cms.classpermission>
  <ClassID>
    <CodeName>DancingGoatCore.HomeSection</CodeName>
    <GUID>87bac113-35ea-402c-b5e5-9de28ea0eae2</GUID>
    <ObjectType>cms.documenttype</ObjectType>
  </ClassID>
  <PermissionDescription>
    <![CDATA[Allows to create new pages under pages for which the user has the 'Create' page-level permission.]]>
  </PermissionDescription>
  <PermissionDisplayInMatrix>True</PermissionDisplayInMatrix>
  <PermissionDisplayName>Create</PermissionDisplayName>
  <PermissionGUID>4298f235-a279-43c2-b09b-929918d32caf</PermissionGUID>
  <PermissionName>CreateSpecific</PermissionName>
  <PermissionOrder>3</PermissionOrder>
</cms.classpermission>