<?xml version="1.0" encoding="utf-8"?>
<media.file>
  <FileCreatedByUserID>
    <CodeName>administrator</CodeName>
    <GUID>6415b8ce-8072-4bcd-8e48-9d7178b826b7</GUID>
    <ObjectType>cms.user</ObjectType>
  </FileCreatedByUserID>
  <FileCreatedWhen>2020-06-01 12:32:35Z</FileCreatedWhen>
  <FileDescription />
  <FileExtension>.jpg</FileExtension>
  <FileGUID>b01ca4dd-7ed1-43c4-9f54-b6fc4d4c1657</FileGUID>
  <FileImageHeight>380</FileImageHeight>
  <FileImageWidth>1080</FileImageWidth>
  <FileLibraryID>
    <CodeName>Graphics</CodeName>
    <GUID>f3cf24e3-8764-42e1-bf85-0d82b1995250</GUID>
    <ObjectType>media.library</ObjectType>
    <Site>
      <CodeName>DancingGoatCore</CodeName>
      <GUID>50ddc16b-9cd7-402f-af01-f3a3feae4ba2</GUID>
      <ObjectType>cms.site</ObjectType>
    </Site>
  </FileLibraryID>
  <FileMimeType>image/jpeg</FileMimeType>
  <FileModifiedByUserID>
    <CodeName>administrator</CodeName>
    <GUID>6415b8ce-8072-4bcd-8e48-9d7178b826b7</GUID>
    <ObjectType>cms.user</ObjectType>
  </FileModifiedByUserID>
  <FileName>banner-default</FileName>
  <FilePath>banner-default.jpg</FilePath>
  <FileSiteID>
    <CodeName>DancingGoatCore</CodeName>
    <GUID>50ddc16b-9cd7-402f-af01-f3a3feae4ba2</GUID>
    <ObjectType>cms.site</ObjectType>
  </FileSiteID>
  <FileSize>75424</FileSize>
  <FileTitle />
</media.file>