<?xml version="1.0" encoding="utf-8"?>
<cms.classpermission>
  <ClassID>
    <CodeName>DancingGoatCore.ManualGrinder</CodeName>
    <GUID>3c47b7bb-e86c-40a9-8b61-6a78a840d6ad</GUID>
    <ObjectType>cms.documenttype</ObjectType>
  </ClassID>
  <PermissionDescription>Allows to browse the content tree.</PermissionDescription>
  <PermissionDisplayInMatrix>True</PermissionDisplayInMatrix>
  <PermissionDisplayName>Browse tree</PermissionDisplayName>
  <PermissionGUID>b1d0a276-3faa-4eba-a18c-7fd6bc997564</PermissionGUID>
  <PermissionName>ExploreTree</PermissionName>
  <PermissionOrder>7</PermissionOrder>
</cms.classpermission>